LICENSE
MANIFEST.in
README.md
requirements.txt
setup.py
img2img/__init__.py
img2img/img2img.py
img2img/img2img_test.py
img2img/version.py
img2img.egg-info/PKG-INFO
img2img.egg-info/SOURCES.txt
img2img.egg-info/dependency_links.txt
img2img.egg-info/entry_points.txt
img2img.egg-info/not-zip-safe
img2img.egg-info/requires.txt
img2img.egg-info/top_level.txt
src/img2img-site.png