Metadata-Version: 2.1
Name: img2img
Version: 0.2.0
Summary: Convert image format.
Home-page: https://github.com/HaveTwoBrush/img2img
Author: Ailln
Author-email: kinggreenhall@gmail.com
License: UNKNOWN
Platform: UNKNOWN
Classifier: Programming Language :: Python :: 3
Classifier: License :: OSI Approved :: MIT License
Classifier: Operating System :: OS Independent
